{
    "Melbourne": 14,
    "Shanghai": 16,
    "Suzuka": 18,
    "Sakhir": 15,
    "Bahrain": 15,
    "Jeddah": 27,
    "Miami": 19,
    "Miami Gardens":19,
    "Montréal": 14,
    "Montreal": 14,
    "Monte Carlo": 19,
    "Monaco": 19,
    "Barcelona": 16,
    "Spielberg": 10,
    "Silverstone": 18,
    "Spa": 19,
    "Spa-Francorchamps": 19,
    "Sochi": 18,
    "Hungaroring": 14,
    "Budapest": 14,
    "Zandvoort": 14,
    "Monza": 11,
    "Imola": 19,
    "Baku": 20,
    "Singapore": 19,
    "Austin": 20,
    "Mexico City": 17,
    "Mexico": 17,
    "São Paulo": 15,
    "Sao Paulo": 15,
    "Las Vegas": 17,
    "Lusail": 16,
    "Yas Marina": 16,
    "Yas Island": 16,
    "Le Castellet": 15,
    "Hockenheim": 17,
    "Mugello": 15,
    "Istanbul": 14,
    "Portimão": 15,
    "Nürburgring": 15,
    "Marina Bay": 19
}
